databrix_hub_extension/__init__.py
databrix_hub_extension/_version.py
databrix_hub_extension-0.1.18.data/data/share/jupyter/labextensions/databrix_hub_extension/package.json
databrix_hub_extension-0.1.18.data/data/share/jupyter/labextensions/databrix_hub_extension/static/509.1d478740c9f694b2af77.js
databrix_hub_extension-0.1.18.data/data/share/jupyter/labextensions/databrix_hub_extension/static/728.e64291c15cbd2e8d57dd.js
databrix_hub_extension-0.1.18.data/data/share/jupyter/labextensions/databrix_hub_extension/static/remoteEntry.a475ab499b87ebc3b5fe.js
databrix_hub_extension-0.1.18.data/data/share/jupyter/labextensions/databrix_hub_extension/static/style.js
databrix_hub_extension-0.1.18.data/data/share/jupyter/labextensions/databrix_hub_extension/static/third-party-licenses.json
databrix_hub_extension-0.1.18.data/data/share/jupyter/labextensions/databrix_hub_extension/install.json
databrix_hub_extension-0.1.18.dist-info/METADATA
databrix_hub_extension-0.1.18.dist-info/WHEEL
databrix_hub_extension-0.1.18.dist-info/licenses/LICENSE
databrix_hub_extension-0.1.18.dist-info/RECORD
