Metadata-Version: 2.3
Name: databrix_hub_extension
Version: 0.1.18
Summary: A JupyterLab extension for hub_extension from databrix Project
Project-URL: Homepage, https://github.com/databrix-org/hub_extension
Project-URL: Bug Tracker, https://github.com/databrix-org/hub_extension/issues
Project-URL: Repository, https://github.com/databrix-org/hub_extension.git
Author-email: Yuqiang Gu <gyq673516081@gmail.com>
License: BSD 3-Clause License
License-File: LICENSE
Keywords: jupyter,jupyterlab,jupyterlab-extension
Classifier: Framework :: Jupyter
Classifier: Framework :: Jupyter :: JupyterLab
Classifier: Framework :: Jupyter :: JupyterLab :: 4
Classifier: Framework :: Jupyter :: JupyterLab :: Extensions
Classifier: Framework :: Jupyter :: JupyterLab :: Extensions :: Prebuilt
Classifier: License :: OSI Approved :: BSD License
Classifier: Programming Language :: Python
Classifier: Programming Language :: Python :: 3
Classifier: Programming Language :: Python :: 3.8
Classifier: Programming Language :: Python :: 3.9
Classifier: Programming Language :: Python :: 3.10
Classifier: Programming Language :: Python :: 3.11
Classifier: Programming Language :: Python :: 3.12
Requires-Python: >=3.8
